ReSubuser/__init__.py
ReSubuser/__main__.py
ReSubuser/cmdline.py
ReSubuser/config.py
ReSubuser/dockerwrap.py
ReSubuser-0.0.19.dist-info/LICENSE.txt
ReSubuser-0.0.19.dist-info/METADATA
ReSubuser-0.0.19.dist-info/RECORD
ReSubuser-0.0.19.dist-info/WHEEL
ReSubuser-0.0.19.dist-info/entry_points.txt
ReSubuser-0.0.19.dist-info/pbr.json
ReSubuser-0.0.19.dist-info/top_level.txt
