Metadata-Version: 2.1
Name: ReSubuser
Version: 0.0.19
Summary: Create Docker container for single application
Home-page: https://framagit.org/who0/ReSubuser
Author: Dominique DERRIER
Author-email: derrierdo@gmail.com
License: GNU General Public License v3.0
Platform: UNKNOWN
Classifier: Programming Language :: Python :: 3
Classifier: Intended Audience :: Information Technology
Classifier: Intended Audience :: End Users/Desktop
Classifier: Development Status :: 4 - Beta
Classifier: Environment :: Console
Classifier: License :: OSI Approved :: GNU General Public License v3 (GPLv3)
